odoo/addons/account_statement_import_camt54/README.rst
odoo/addons/account_statement_import_camt54/__init__.py
odoo/addons/account_statement_import_camt54/__manifest__.py
odoo/addons/account_statement_import_camt54/i18n/account_statement_import_camt54.pot
odoo/addons/account_statement_import_camt54/models/__init__.py
odoo/addons/account_statement_import_camt54/models/account_journal.py
odoo/addons/account_statement_import_camt54/models/account_statement_import.py
odoo/addons/account_statement_import_camt54/models/parser.py
odoo/addons/account_statement_import_camt54/readme/CONTRIBUTORS.rst
odoo/addons/account_statement_import_camt54/readme/CREDITS.rst
odoo/addons/account_statement_import_camt54/readme/DESCRIPTION.rst
odoo/addons/account_statement_import_camt54/static/description/icon.png
odoo/addons/account_statement_import_camt54/static/description/index.html
odoo/addons/account_statement_import_camt54/tests/__init__.py
odoo/addons/account_statement_import_camt54/tests/test_get_partner_ref.py
odoo/addons/account_statement_import_camt54/tests/test_statement.py
odoo14_addon_account_statement_import_camt54-14.0.1.1.0.dist-info/METADATA
odoo14_addon_account_statement_import_camt54-14.0.1.1.0.dist-info/WHEEL
odoo14_addon_account_statement_import_camt54-14.0.1.1.0.dist-info/top_level.txt
odoo14_addon_account_statement_import_camt54-14.0.1.1.0.dist-info/RECORD
