Metadata-Version: 2.1
Name: odoo14-addon-account-statement-import-camt54
Version: 14.0.1.1.0
Summary: Bank Account Camt54 Import
Home-page: https://github.com/OCA/bank-statement-import
Author: camptocamp, Odoo Community Association (OCA)
Author-email: support@odoo-community.org
License: AGPL-3
Platform: UNKNOWN
Classifier: Programming Language :: Python
Classifier: Framework :: Odoo
Classifier: License :: OSI Approved :: GNU Affero General Public License v3
Requires-Python: >=3.6
Requires-Dist: odoo14-addon-account-statement-import-camt
Requires-Dist: odoo (<14.1dev,>=14.0a)
